betag/__init__.py
betag/choice.py
betag/history.py
betag/main.py
betag-0.1.5.dist-info/entry_points.txt
betag-0.1.5.dist-info/WHEEL
betag-0.1.5.dist-info/METADATA
betag-0.1.5.dist-info/RECORD
