Metadata-Version: 2.1
Name: betag
Version: 0.1.5
Summary: Label data easily!
Author: Jaume Ferrarons
Author-email: jaume.ferrarons@gmail.com
Requires-Python: >=3.7.1,<4.0.0
Classifier: Programming Language :: Python :: 3
Classifier: Programming Language :: Python :: 3.10
Classifier: Programming Language :: Python :: 3.8
Classifier: Programming Language :: Python :: 3.9
Requires-Dist: pandas (>=1.3,<2.0)
Requires-Dist: streamlit (>=1.5.1,<2.0.0)
